opm/_common.py
opm/opmcommon_python.cpython-314-x86_64-linux-gnu.so
opm/io/__init__.py
opm/io/log.py
opm/io/deck/__init__.py
opm/io/ecl/__init__.py
opm/io/ecl_state/__init__.py
opm/io/parser/__init__.py
opm/io/schedule/__init__.py
opm/io/sim/__init__.py
opm/io/summary/__init__.py
opm/ml/ml_tools/__init__.py
opm/ml/ml_tools/kerasify.py
opm/ml/ml_tools/scaler_layers.py
opm/tools/__init__.py
opm/tools/time_vector.py
opm/util/__init__.py
opm.libs/libgomp-e985bcbb.so.1.0.0
opm_embedded/__init__.py
opm-2025.10.dist-info/METADATA
opm-2025.10.dist-info/WHEEL
opm-2025.10.dist-info/top_level.txt
opm-2025.10.dist-info/RECORD
opm-2025.10.dist-info/sboms/auditwheel.cdx.json
